playlab_api/__init__.py
playlab_api/client.py
playlab_api-0.1.4.dist-info/METADATA
playlab_api-0.1.4.dist-info/WHEEL
playlab_api-0.1.4.dist-info/top_level.txt
playlab_api-0.1.4.dist-info/RECORD
