Metadata-Version: 2.4
Name: playlab-api
Version: 0.1.4
Summary: A Python client for the Playlab API
Home-page: https://github.com/teaghan/playlab-python
Author: Teaghan
Classifier: Development Status :: 3 - Alpha
Classifier: Intended Audience :: Developers
Classifier: License :: OSI Approved :: MIT License
Classifier: Programming Language :: Python :: 3
Requires-Python: >=3.7
Requires-Dist: requests
Requires-Dist: ipython
Dynamic: author
Dynamic: classifier
Dynamic: description
Dynamic: description-content-type
Dynamic: home-page
Dynamic: requires-dist
Dynamic: requires-python
Dynamic: summary
